[
  {
    "userType": "user",
    "fullName": "aasdq",
    "mobile": "a",
    "email": "a@gmail.com",
    "camera_ip": "a",
    "police_number": "a",
    "fire_number": "aa",
    "ambulance_number": "a",
    "alert_email": "a@gmail.com",
    "department": "",
    "designation": "",
    "employee_id": "",
    "official_phone": "",
    "official_email": "",
    "office_address": "",
    "password": "a",
    "confirm_password": "a",
    "phone": "",
    "address": "",
    "about": ""
  }
]